logentries_api/__init__.py
logentries_api/alerts.py
logentries_api/base.py
logentries_api/exceptions.py
logentries_api/logs.py
logentries_api/resources.py
logentries_api/special_alerts.py
logentries_api/version.py
logentries_api/tests/__init__.py
logentries_api/tests/base_tests.py
logentries_api/tests/logs_tests.py
logentries_api/tests/resources_tests.py
logentries_api/tests/special_alerts_tests.py
logentries_api/tests/test_alerts.py
logentries_api/tests/tests.py
python_logentries_api-0.7.dist-info/DESCRIPTION.rst
python_logentries_api-0.7.dist-info/METADATA
python_logentries_api-0.7.dist-info/metadata.json
python_logentries_api-0.7.dist-info/pbr.json
python_logentries_api-0.7.dist-info/RECORD
python_logentries_api-0.7.dist-info/top_level.txt
python_logentries_api-0.7.dist-info/WHEEL
