Metadata-Version: 2.0
Name: python-logentries-api
Version: 0.7
Summary: A python wrapper for the Logentries API
Home-page: https://github.com/ambitioninc/python-logentries-api
Author: Micah Hausler
Author-email: opensource@ambition.com
License: MIT
Keywords: logs,logentries
Platform: UNKNOWN
Classifier: Programming Language :: Python :: 2.7
Classifier: Programming Language :: Python :: 3.3
Classifier: Programming Language :: Python :: 3.4
Classifier: Intended Audience :: Developers
Classifier: License :: OSI Approved :: MIT License
Classifier: Operating System :: OS Independent
Requires-Dist: requests (>=2.7.0)
Requires-Dist: six (>=1.9.0)
Requires-Dist: enum34 (>=1.0.4)
